githubiot/__init__.py
githubiot/app.py
githubiot/app_manager.py
githubiot/cli.py
githubiot/splash.py
githubiot/templates/config.json
githubiot/templates/main.py
githubiot/templates/requirements.txt
githubiot-1.0.7.dist-info/licenses/LICENSE
githubiot-1.0.7.dist-info/METADATA
githubiot-1.0.7.dist-info/WHEEL
githubiot-1.0.7.dist-info/entry_points.txt
githubiot-1.0.7.dist-info/top_level.txt
githubiot-1.0.7.dist-info/RECORD
