Metadata-Version: 2.4
Name: githubiot
Version: 1.0.7
Summary: GitHubIoT is a comprehensive toolkit designed to simplify the visualization of IoT (Internet of Things) data with seamless GitHub integration.
Home-page: https://github.com/4211421036/githubiotpy
Author: GALIH RIDHO UTOMO, Fionita Fahra Azzahra
Author-email: GALIH RIDHO UTOMO <g4lihru@students.unnes.ac.id>, Fionita Fahra Azzahra <fionitafahra13@students.unnes.ac.id>
Project-URL: Documentation, https://github.com/4211421036/githubiotpy/README.md
Project-URL: Source, https://github.com/4211421036/githubiotpy
Project-URL: Homepage, https://4211421036.github.io/githubiotpy/
Keywords: Github,IoT,Arduino IDE,Python Modules,ESP32,ESP8266,webApp
Classifier: Programming Language :: Python :: 3
Classifier: License :: OSI Approved :: MIT License
Classifier: Operating System :: OS Independent
Requires-Python: >=3.6
License-File: LICENSE
Requires-Dist: requests>=2.26.0
Requires-Dist: matplotlib>=3.5.0
Requires-Dist: numpy>=1.21.0
Requires-Dist: pyinstaller>=5.0.0
Dynamic: author
Dynamic: home-page
Dynamic: license-file
Dynamic: requires-python
